{
  "type": "minecraft:crafting_shaped",
  "show_notification": true,
  "group": "healmeter",
  "category": "misc",
  "pattern": [
    "123",
    "456",
    "789"
  ],
  "key": {
    "1": [
      "minecraft:lightning_rod"
    ],
    "2": [
      "minecraft:ender_pearl"
    ],
    "3": [
      "minecraft:spyglass"
    ],
    "4": [
      "minecraft:recovery_compass"
    ],
    "5": [
      "minecraft:echo_shard"
    ],
    "6": [
      "minecraft:ender_pearl"
    ],
    "7": [
      "minecraft:echo_shard"
    ],
    "8": [
      "minecraft:breeze_rod"
    ],
    "9": [
      "minecraft:breeze_rod"
    ]
  },
  "result": {
    "id": "minecraft:recovery_compass",
    "components": {
      "minecraft:item_name": {
        "text": "Измеритель здоровья",
        "color": "white",
        "bold": false,
        "italic": false,
        "underlined": false,
        "strikethrough": false,
        "obfuscated": false
      },
      "minecraft:custom_data": {
        "isHpMeter": true
      },
      "minecraft:item_model": "terf:tool/shrink_ray"
    },
    "count": 1
  }
}